comodels/__init__.py
comodels/penn.py
comodels/sir.py
comodels/utils.py
covid_modeling-0.1.1.dist-info/LICENSE.txt
covid_modeling-0.1.1.dist-info/METADATA
covid_modeling-0.1.1.dist-info/WHEEL
covid_modeling-0.1.1.dist-info/top_level.txt
covid_modeling-0.1.1.dist-info/RECORD
