Metadata-Version: 2.1
Name: covid-modeling
Version: 0.1.1
Summary: COVID-19 Modeling
Home-page: https://github.com/josephsdavid/COVID_modeling
Maintainer: David Josephs
Maintainer-email: josephsd@smu.edu
License: MIT
Platform: UNKNOWN
Classifier: Programming Language :: Python :: 3
Classifier: License :: OSI Approved :: MIT License
Classifier: Operating System :: OS Independent
